src/__init__.py
src/__main__.py
src/parsing.py
src/scraping.py
available_nerdfont-1.0.1.dist-info/METADATA
available_nerdfont-1.0.1.dist-info/WHEEL
available_nerdfont-1.0.1.dist-info/entry_points.txt
available_nerdfont-1.0.1.dist-info/RECORD
